<!-- IK Plugins -->
<library path="ik_solver_plugins">
  <!-- MoveIt IK Solver -->
  <class name="moveit_reach_plugins/ik/MoveItIKSolver" type="moveit_reach_plugins::ik::MoveItIKSolver" base_class_type="reach::plugins::IKSolverBase">
    <description>
      An inverse kinematics solver plugin which utilizes the MoveIt framework for solving robot inverse kinematics with respect to a given planning environment
    </description>
  </class>
  <!-- Discretized MoveIt IK Solver -->
  <class name="moveit_reach_plugins/ik/DiscretizedMoveItIKSolver" type="moveit_reach_plugins::ik::DiscretizedMoveItIKSolver" base_class_type="reach::plugins::IKSolverBase">
    <description>
      An inverse kinematics solver plugin which utilizes the MoveIt framework for solving robot inverse kinematics with respect to a given planning environment
      This plugin discretizes the target pose around the Z-axis and outputs the solution with the highest score
    </description>
  </class>
  <class name="moveit_reach_plugins/ik/CartesianRetrievalIKSolver" type="moveit_reach_plugins::ik::CartesianRetrievalIKSolver" base_class_type="reach::plugins::IKSolverBase">
    <description>
      An inverse kinematics solver plugin which utilizes the MoveIt framework for solving robot inverse kinematics with respect to a given planning environment
      This plugin additionally does retrieval path computation from the specified pose.
    </description>
  </class>
</library>
